tests/__init__.py
tests/sanity_test.py
vstask/Timer.py
vstask/__init__.py
vstask/__version__.py
vstask/cli.py
vstask/completion.py
vstask/vstask.py
vstask-2.0.2.dist-info/LICENSE
vstask-2.0.2.dist-info/METADATA
vstask-2.0.2.dist-info/WHEEL
vstask-2.0.2.dist-info/entry_points.txt
vstask-2.0.2.dist-info/top_level.txt
vstask-2.0.2.dist-info/RECORD
