Metadata-Version: 2.1
Name: vstask
Version: 2.0.2
Summary: CLI for VSCode tasks
Home-page: https://github.com/cmccandless/vstask
Author: Corey McCandless
Author-email: crm1994@gmail.com
License: UNKNOWN
Platform: UNKNOWN
Classifier: Programming Language :: Python :: 3
Classifier: License :: OSI Approved :: MIT License
Classifier: Operating System :: OS Independent
